refactx/SimpleCache.py
refactx/__init__.py
refactx/api.py
refactx/generate.py
refactx/httpindex.py
refactx/index.py
refactx/prompt_base.py
refactx/prompt_reasoning.py
refactx/cli/__init__.py
refactx/cli/debug_postgres.py
refactx/cli/populate_postgres.py
refactx-0.1.2.dist-info/licenses/LICENSE
refactx-0.1.2.dist-info/METADATA
refactx-0.1.2.dist-info/WHEEL
refactx-0.1.2.dist-info/entry_points.txt
refactx-0.1.2.dist-info/top_level.txt
refactx-0.1.2.dist-info/RECORD
