Metadata-Version: 2.4
Name: refactx
Version: 0.1.2
Summary: Refactx package
Author: Riccardo Pozzi
License-Expression: Apache-2.0
Project-URL: Homepage, https://github.com/rpo19/ReFactX
Project-URL: Repository, https://github.com/rpo19/ReFactX
Project-URL: Bug Tracker, https://github.com/rpo19/ReFactX/issues
Requires-Python: >=3.8
License-File: LICENSE
Requires-Dist: tqdm
Requires-Dist: python-dotenv
Requires-Dist: click
Requires-Dist: psycopg[binary]>=3.0
Requires-Dist: cachetools
Requires-Dist: requests
Provides-Extra: torch
Requires-Dist: torch; extra == "torch"
Requires-Dist: transformers>=4.0; extra == "torch"
Requires-Dist: accelerate; extra == "torch"
Provides-Extra: httpindex
Requires-Dist: flask; extra == "httpindex"
Requires-Dist: gunicorn; extra == "httpindex"
Dynamic: license-file
